[
    {
        "titulo": "How The Engie Brasil Energia (BOVESPA:EGIE3) Narrative Is Evolving Around The New R$34 Target",
        "link": "https://finance.yahoo.com/markets/stocks/articles/engie-brasil-energia-bovespa-egie3-211251215.html",
        "fonte": "Simply Wall St.",
        "data": "Data desconhecida"
    },
    {
        "titulo": "How The Engie Brasil Energia (BOVESPA:EGIE3) Narrative Is Shifting With The Updated Fair Value",
        "link": "https://finance.yahoo.com/markets/stocks/articles/engie-brasil-energia-bovespa-egie3-001648496.html",
        "fonte": "Simply Wall St.",
        "data": "Data desconhecida"
    },
    {
        "titulo": "How The Engie Brasil Energia (BOVESPA:EGIE3) Story Evolves With A Steady Analyst Outlook",
        "link": "https://finance.yahoo.com/markets/stocks/articles/engie-brasil-energia-bovespa-egie3-070727131.html",
        "fonte": "Simply Wall St.",
        "data": "Data desconhecida"
    },
    {
        "titulo": "Why ENGIE BRASL EGA (EGIEY) is a Great Dividend Stock Right Now",
        "link": "https://finance.yahoo.com/news/why-engie-brasl-ega-egiey-154505149.html",
        "fonte": "Zacks",
        "data": "Data desconhecida"
    },
    {
        "titulo": "Is Algonquin Power & Utilities (AQN) Outperforming Other Utilities Stocks This Year?",
        "link": "https://finance.yahoo.com/news/algonquin-power-utilities-aqn-outperforming-144004875.html",
        "fonte": "Zacks",
        "data": "Data desconhecida"
    },
    {
        "titulo": "Why ENGIE BRASL EGA (EGIEY) is a Top Dividend Stock for Your Portfolio",
        "link": "https://finance.yahoo.com/news/why-engie-brasl-ega-egiey-164503079.html",
        "fonte": "Zacks",
        "data": "Data desconhecida"
    },
    {
        "titulo": "Is Energias de Portugal (EDPFY) Stock Outpacing Its Utilities Peers This Year?",
        "link": "https://finance.yahoo.com/news/energias-portugal-edpfy-stock-outpacing-144002986.html",
        "fonte": "Zacks",
        "data": "Data desconhecida"
    },
    {
        "titulo": "Why Analysts See Engie Brasil Energia (BOVESPA:EGIE3) Story Shifting After Neutral Rating Call",
        "link": "https://finance.yahoo.com/news/why-analysts-see-engie-brasil-130811208.html",
        "fonte": "Simply Wall St.",
        "data": "Data desconhecida"
    },
    {
        "titulo": "How Recent Moves Are Rewriting the Investment Story for Engie Brasil Energia",
        "link": "https://finance.yahoo.com/news/recent-moves-rewriting-investment-story-220645525.html",
        "fonte": "Simply Wall St.",
        "data": "Data desconhecida"
    },
    {
        "titulo": "What Catalysts Are Shaping the Narrative for Engie Brasil Energia?",
        "link": "https://finance.yahoo.com/news/catalysts-shaping-narrative-engie-brasil-010905698.html",
        "fonte": "Simply Wall St.",
        "data": "Data desconhecida"
    }
]