[
    {
        "titulo": "Eneva SA (BSP:ENEV3) Q4 2025 Earnings Call Highlights: Record EBITDA and Strategic Growth ...",
        "link": "https://finance.yahoo.com/news/eneva-sa-bsp-enev3-q4-010235184.html",
        "fonte": "GuruFocus.com",
        "data": "Data desconhecida"
    },
    {
        "titulo": "Eneva SA (BSP:ENEV3) Q3 2025 Earnings Call Highlights: Record EBITDA and Strategic Growth Amid ...",
        "link": "https://finance.yahoo.com/news/eneva-sa-bsp-enev3-q3-210519057.html",
        "fonte": "GuruFocus.com",
        "data": "Data desconhecida"
    },
    {
        "titulo": "Accenture plc (ACN) and Google Cloud Partners with Eneva",
        "link": "https://finance.yahoo.com/news/accenture-plc-acn-google-cloud-155512070.html",
        "fonte": "Insider Monkey",
        "data": "Data desconhecida"
    },
    {
        "titulo": "Accenture (ACN) Valuation in Focus After Eneva and Google Cloud Collaboration Spurs Digital Growth Narrative",
        "link": "https://finance.yahoo.com/news/accenture-acn-valuation-focus-eneva-123908457.html",
        "fonte": "Simply Wall St.",
        "data": "Data desconhecida"
    }
]