[
    {
        "titulo": "Lojas Renner SA (BSP:LREN3) Q4 2025 Earnings Call Highlights: Record Net Income and Strategic ...",
        "link": "https://finance.yahoo.com/news/lojas-renner-sa-bsp-lren3-010255639.html",
        "fonte": "GuruFocus.com",
        "data": "Data desconhecida"
    },
    {
        "titulo": "Google Cloud lands deal with Palo Alto Networks 'approaching $10 billion,' per source",
        "link": "https://finance.yahoo.com/news/google-cloud-lands-deal-palo-130205390.html",
        "fonte": "Reuters",
        "data": "Data desconhecida"
    },
    {
        "titulo": "Brazil apparel firm Lojas Renner expects softer results before 2026 improvement, CFO says",
        "link": "https://ca.finance.yahoo.com/news/brazil-apparel-firm-lojas-renner-113408783.html",
        "fonte": "Reuters",
        "data": "Data desconhecida"
    }
]